{
  "name": "scan-text",
  "viewBox": "0 0 24 24",
  "strokeWidth": 2,
  "strokeLinecap": "round",
  "strokeLinejoin": "round",
  "elements": [
    {
      "type": "path",
      "d": "M3 7V5a2 2 0 0 1 2-2h2"
    },
    {
      "type": "path",
      "d": "M17 3h2a2 2 0 0 1 2 2v2"
    },
    {
      "type": "path",
      "d": "M21 17v2a2 2 0 0 1-2 2h-2"
    },
    {
      "type": "path",
      "d": "M7 21H5a2 2 0 0 1-2-2v-2"
    },
    {
      "type": "path",
      "d": "M7 8h8"
    },
    {
      "type": "path",
      "d": "M7 12h10"
    },
    {
      "type": "path",
      "d": "M7 16h6"
    }
  ],
  "animation": null
}